Metadata-Version: 1.0
Name: weimob123
Version: 2.0
Summary: weimob123 for world
Home-page: https://github.com/zhucaixiangtest/test123
Author: cx123
Author-email: zcx@zcx-t.top
License: MIT
Platform: UNKNOWN
